{
    "DPAD_CONFIG": "0380EF20",
    "DPAD_TEXTURE": "03811C80",
    "EXT_MSG_DATA_FILE": "0380F7C8",
    "EXT_MSG_TABLE": "03810C00",
    "EXT_MSG_TABLE_COUNT": "0380F780",
    "EXT_OBJECTS": "0380F7E8",
    "FONT_TEXTURE": "03812C80",
    "G_C_HEAP": "03820000",
    "G_PAYLOAD_ADDR": "03800000",
    "HASH_ICONS": "0380EFB4",
    "HUD_COLOR_CONFIG": "0380EFFC",
    "ITEM_OVERRIDE_COUNT": "0380F77C",
    "ITEM_OVERRIDE_ENTRIES": "0380F980",
    "MISC_CONFIG": "0380F5B4",
    "MMR_CONFIG": "0380F0DC",
    "MUSIC_CONFIG": "0380F5DC",
    "PAYLOAD_END": "03814150",
    "PAYLOAD_START": "03800000",
    "SAVE_FILE_CONFIG": "0380F670",
    "TOWN_FAIRY_BYTES": "03810F00",
    "WORLD_COLOR_CONFIG": "0380F724",
    "forceSpawn": "0380F7D8",
    "gExternalEffects": "0380EF3C",
    "gHeapNext": "0380F7E4",
    "gObjheap": "03810E00",
    "gObjheapItems": "03810E18",
    "gPlayUpdateInput": "0380F868",
    "gSetupDb": "0380F6F0",
    "gSpriteDpad": "0380F6E0",
    "gSpriteFairy": "0380F6A0",
    "gSpriteFont": "0380F6D0",
    "gSpriteIcon": "0380F6C0",
    "gSpriteIcon24": "0380F6B0",
    "gStaticAddressConfig": "0380F718"
}
